prob_distributionrk3/Binomialdistribution.py
prob_distributionrk3/Gaussiandistribution.py
prob_distributionrk3/Generaldistribution.py
prob_distributionrk3/__init__.py
prob_distributionrk3-1.0.dist-info/DESCRIPTION.rst
prob_distributionrk3-1.0.dist-info/METADATA
prob_distributionrk3-1.0.dist-info/RECORD
prob_distributionrk3-1.0.dist-info/WHEEL
prob_distributionrk3-1.0.dist-info/metadata.json
prob_distributionrk3-1.0.dist-info/top_level.txt
